airflow_cdk/__init__.py
airflow_cdk/cdk.py
airflow_cdk/tasks.py
airflow_cdk/templates/__init__.py
airflow_cdk/templates/example_dag.py
airflow_cdk-0.6.0.dist-info/LICENSE
airflow_cdk-0.6.0.dist-info/METADATA
airflow_cdk-0.6.0.dist-info/WHEEL
airflow_cdk-0.6.0.dist-info/top_level.txt
airflow_cdk-0.6.0.dist-info/RECORD
