Metadata-Version: 2.1
Name: airflow-cdk
Version: 0.6.0
Summary: Custom cdk constructs for apache airflow
Home-page: https://github.com/knowsuchagency/airflow-cdk
Author: Stephan Fitzpatrick
Author-email: stephan@knowsuchagency.com
License: UNKNOWN
Keywords: aws,cdk,airflow,k8s
Platform: UNKNOWN
Classifier: Development Status :: 4 - Beta
Classifier: Intended Audience :: Developers
Classifier: License :: OSI Approved :: Apache Software License
Classifier: Programming Language :: JavaScript
Classifier: Programming Language :: Python :: 3 :: Only
Classifier: Programming Language :: Python :: 3.6
Classifier: Programming Language :: Python :: 3.7
Classifier: Programming Language :: Python :: 3.8
Classifier: Topic :: Software Development :: Code Generators
Classifier: Topic :: Utilities
Classifier: Typing :: Typed
Requires-Python: >=3.6
Requires-Dist: aws-cdk.core (>=1.51.0)
Requires-Dist: aws-cdk.aws-ecs (>=1.51.0)
Requires-Dist: aws-cdk.aws-ecs-patterns (>=1.51.0)
Requires-Dist: aws-cdk.aws-rds (>=1.51.0)
Requires-Dist: aws-cdk.aws-s3 (>=1.51.0)
Requires-Dist: aws-cdk.aws-elasticloadbalancingv2 (>=1.51.0)
Provides-Extra: dev
Requires-Dist: qypi ; extra == 'dev'
Requires-Dist: klaxon ; extra == 'dev'
Requires-Dist: pytest ; extra == 'dev'
Requires-Dist: toml ; extra == 'dev'
Requires-Dist: black ; extra == 'dev'
Requires-Dist: twine ; extra == 'dev'
Requires-Dist: invoke ; extra == 'dev'
Requires-Dist: jinja2 ; extra == 'dev'
Requires-Dist: apache-airflow[aws,celery,postgres] (>=1.10.10) ; extra == 'dev'
